python/__init__.py
python/data_set/__init__.py
python/data_set/generate_prediction_data.py
python/data_set/gg_data_set.py
python/data_set/img_data_set.py
python/data_set/ts_data_set.py
python/hparams/__init__.py
python/hparams/hyperparameters.py
python/image/__init__.py
python/model/__init__.py
python/model/nn_model.py
python/model/one_dim_cnn_model.py
python/model/operation.py
python/model/tf_sample_cnn_model.py
python/model/two_dim_cnn_model.py
python/model/two_dim_cnn_model_v2.py
python/model/user.py
python/optimizer/AdaBound.py
python/optimizer/__init__.py
python/test/__init__.py
python/test/data_set/__init__.py
python/test/data_set/test_gg_data_set.py
python/test/data_set/test_ts_data.py
python/test/data_set/test_ts_data_set.py
python/test/model/__init__.py
python/test/model/test_user.py
python/test/utils/__init__.py
python/test/utils/test_hash_array.py
python/test/utils/test_lap_time.py
python/test/utils/test_user.py
python/utils/__init__.py
python/utils/gg_mongo_data_base.py
python/utils/gg_setting.py
python/utils/hash_array.py
python/utils/jwt_util.py
python/utils/lap_time.py
python/utils/onnx_util.py
python/utils/proc.py
python/utils/tf_log_to_csv.py
smalltrain/__init__.py
smalltrain/data_set/__init__.py
smalltrain/data_set/generate_prediction_data.py
smalltrain/data_set/gg_data_set.py
smalltrain/data_set/img_data_set.py
smalltrain/data_set/ts_data_set.py
smalltrain/hparams/__init__.py
smalltrain/hparams/hyperparameters.py
smalltrain/image/__init__.py
smalltrain/model/__init__.py
smalltrain/model/nn_model.py
smalltrain/model/one_dim_cnn_model.py
smalltrain/model/operation.py
smalltrain/model/tf_sample_cnn_model.py
smalltrain/model/two_dim_cnn_model.py
smalltrain/model/two_dim_cnn_model_v2.py
smalltrain/model/user.py
smalltrain/optimizer/AdaBound.py
smalltrain/optimizer/__init__.py
smalltrain/test/__init__.py
smalltrain/test/data_set/__init__.py
smalltrain/test/data_set/test_gg_data_set.py
smalltrain-0.2.1.0.dist-info/DESCRIPTION.rst
smalltrain-0.2.1.0.dist-info/METADATA
smalltrain-0.2.1.0.dist-info/RECORD
smalltrain-0.2.1.0.dist-info/WHEEL
smalltrain-0.2.1.0.dist-info/metadata.json
smalltrain-0.2.1.0.dist-info/top_level.txt
