Metadata-Version: 2.0
Name: smalltrain
Version: 0.2.1.0
Summary: SmallTrain
Home-page: https://www.geek-guild.jp
Author: Geek Guild Co., Ltd.
Author-email: labo@geek-guild.jp
License: UNKNOWN
Platform: UNKNOWN
